django_uicomponents/__init__.py
django_uicomponents/apps.py
django_uicomponents/settings.py
django_uicomponents/version.py
django_uicomponents/templates/django_uicomponent.html
django_uicomponents/templatetags/__init__.py
django_uicomponents/templatetags/components.py
tests/__init__.py
tests/settings.py
tests/test_templatetags.py
django_uicomponents-0.1.0.dist-info/LICENSE
django_uicomponents-0.1.0.dist-info/METADATA
django_uicomponents-0.1.0.dist-info/WHEEL
django_uicomponents-0.1.0.dist-info/top_level.txt
django_uicomponents-0.1.0.dist-info/RECORD
