Metadata-Version: 2.1
Name: django-uicomponents
Version: 0.1.0
Summary: Reusable UI components for your Django templates
Home-page: https://github.com/koenwoortman/django-uicomponents
Author: Koen Woortman
Author-email: koensw@outlook.com
License: MIT
Project-URL: Source, https://github.com/koenwoortman/django-uicomponents
Platform: UNKNOWN
Classifier: Framework :: Django
Classifier: License :: OSI Approved :: MIT License
Classifier: Programming Language :: Python :: 3
Requires-Python: >=3.6
Requires-Dist: Django (>=2.2)
